LICENSE
MANIFEST.in
README.md
pyproject.toml
setup.cfg
setup.py
auto_router/__init__.py
auto_router/apps.py
auto_router/core.py
auto_router/tests.py
djangoautorouter.egg-info/PKG-INFO
djangoautorouter.egg-info/SOURCES.txt
djangoautorouter.egg-info/dependency_links.txt
djangoautorouter.egg-info/requires.txt
djangoautorouter.egg-info/top_level.txt