Metadata-Version: 2.1
Name: djangoautorouter
Version: 0.1
Summary: Fast Django Routing
Home-page: https://www.example.com/
Author: MonoliTI
Author-email: brenodega28@gmail.com
License: MIT License
Classifier: Environment :: Web Environment
Classifier: Framework :: Django
Classifier: Framework :: Django :: 3.0
Classifier: Intended Audience :: Developers
Classifier: Operating System :: OS Independent
Classifier: Programming Language :: Python
Classifier: Programming Language :: Python :: 3
Classifier: Programming Language :: Python :: 3 :: Only
Requires-Python: >=3.6
License-File: LICENSE
